[
 {
  "allow_in_quick_entry": 0,
  "allow_on_submit": 0,
  "bold": 0,
  "collapsible": 0,
  "collapsible_depends_on": null,
  "columns": 0,
  "default": null,
  "depends_on": null,
  "description": null,
  "docstatus": 0,
  "doctype": "Custom Field",
  "dt": "Tax Withholding Category",
  "fetch_from": null,
  "fetch_if_empty": 0,
  "fieldname": "custom_section",
  "fieldtype": "Link",
  "hidden": 0,
  "hide_border": 0,
  "hide_days": 0,
  "hide_seconds": 0,
  "ignore_user_permissions": 0,
  "ignore_xss_filter": 0,
  "in_global_search": 0,
  "in_list_view": 0,
  "in_preview": 0,
  "in_standard_filter": 0,
  "insert_after": "category_details_section",
  "is_system_generated": 0,
  "is_virtual": 0,
  "label": "Section",
  "length": 0,
  "mandatory_depends_on": null,
  "modified": "2023-12-27 18:46:18.888162",
  "module": "Ambica Finance",
  "name": "Tax Withholding Category-custom_section",
  "no_copy": 0,
  "non_negative": 0,
  "options": "TDS Master",
  "permlevel": 0,
  "precision": "",
  "print_hide": 0,
  "print_hide_if_no_value": 0,
  "print_width": null,
  "read_only": 0,
  "read_only_depends_on": null,
  "report_hide": 0,
  "reqd": 0,
  "search_index": 0,
  "sort_options": 0,
  "translatable": 0,
  "unique": 0,
  "width": null
 },
 {
  "allow_in_quick_entry": 0,
  "allow_on_submit": 0,
  "bold": 0,
  "collapsible": 0,
  "collapsible_depends_on": null,
  "columns": 0,
  "default": null,
  "depends_on": null,
  "description": null,
  "docstatus": 0,
  "doctype": "Custom Field",
  "dt": "Supplier",
  "fetch_from": null,
  "fetch_if_empty": 0,
  "fieldname": "custom_company",
  "fieldtype": "Link",
  "hidden": 0,
  "hide_border": 0,
  "hide_days": 0,
  "hide_seconds": 0,
  "ignore_user_permissions": 0,
  "ignore_xss_filter": 0,
  "in_global_search": 0,
  "in_list_view": 0,
  "in_preview": 0,
  "in_standard_filter": 0,
  "insert_after": "supplier_name",
  "is_system_generated": 0,
  "is_virtual": 0,
  "label": "Company",
  "length": 0,
  "mandatory_depends_on": null,
  "modified": "2023-12-27 18:46:19.334448",
  "module": "Ambica Finance",
  "name": "Supplier-custom_company",
  "no_copy": 0,
  "non_negative": 0,
  "options": "Company",
  "permlevel": 0,
  "precision": "",
  "print_hide": 0,
  "print_hide_if_no_value": 0,
  "print_width": null,
  "read_only": 0,
  "read_only_depends_on": null,
  "report_hide": 0,
  "reqd": 0,
  "search_index": 0,
  "sort_options": 0,
  "translatable": 0,
  "unique": 0,
  "width": null
 },
 {
  "allow_in_quick_entry": 0,
  "allow_on_submit": 0,
  "bold": 0,
  "collapsible": 0,
  "collapsible_depends_on": null,
  "columns": 0,
  "default": null,
  "depends_on": null,
  "description": null,
  "docstatus": 0,
  "doctype": "Custom Field",
  "dt": "Tax Withholding Category",
  "fetch_from": null,
  "fetch_if_empty": 0,
  "fieldname": "custom_sub_category",
  "fieldtype": "Select",
  "hidden": 0,
  "hide_border": 0,
  "hide_days": 0,
  "hide_seconds": 0,
  "ignore_user_permissions": 0,
  "ignore_xss_filter": 0,
  "in_global_search": 0,
  "in_list_view": 0,
  "in_preview": 0,
  "in_standard_filter": 0,
  "insert_after": "category_name",
  "is_system_generated": 0,
  "is_virtual": 0,
  "label": "Sub Category",
  "length": 0,
  "mandatory_depends_on": null,
  "modified": "2023-12-27 18:46:19.092210",
  "module": "Ambica Finance",
  "name": "Tax Withholding Category-custom_sub_category",
  "no_copy": 0,
  "non_negative": 0,
  "options": "Propritorship\nOther",
  "permlevel": 0,
  "precision": "",
  "print_hide": 0,
  "print_hide_if_no_value": 0,
  "print_width": null,
  "read_only": 0,
  "read_only_depends_on": null,
  "report_hide": 0,
  "reqd": 0,
  "search_index": 0,
  "sort_options": 0,
  "translatable": 1,
  "unique": 0,
  "width": null
 },
 {
  "allow_in_quick_entry": 0,
  "allow_on_submit": 0,
  "bold": 0,
  "collapsible": 0,
  "collapsible_depends_on": null,
  "columns": 0,
  "default": null,
  "depends_on": null,
  "description": null,
  "docstatus": 0,
  "doctype": "Custom Field",
  "dt": "Journal Entry",
  "fetch_from": null,
  "fetch_if_empty": 0,
  "fieldname": "custom_from_date",
  "fieldtype": "Date",
  "hidden": 0,
  "hide_border": 0,
  "hide_days": 0,
  "hide_seconds": 0,
  "ignore_user_permissions": 0,
  "ignore_xss_filter": 0,
  "in_global_search": 0,
  "in_list_view": 0,
  "in_preview": 0,
  "in_standard_filter": 0,
  "insert_after": "voucher_type",
  "is_system_generated": 0,
  "is_virtual": 0,
  "label": "From Date",
  "length": 0,
  "mandatory_depends_on": null,
  "modified": "2023-12-27 18:46:19.872423",
  "module": "Ambica Finance",
  "name": "Journal Entry-custom_from_date",
  "no_copy": 0,
  "non_negative": 0,
  "options": null,
  "permlevel": 0,
  "precision": "",
  "print_hide": 0,
  "print_hide_if_no_value": 0,
  "print_width": null,
  "read_only": 1,
  "read_only_depends_on": null,
  "report_hide": 0,
  "reqd": 0,
  "search_index": 0,
  "sort_options": 0,
  "translatable": 0,
  "unique": 0,
  "width": null
 },
 {
  "allow_in_quick_entry": 0,
  "allow_on_submit": 0,
  "bold": 0,
  "collapsible": 0,
  "collapsible_depends_on": null,
  "columns": 0,
  "default": null,
  "depends_on": null,
  "description": null,
  "docstatus": 0,
  "doctype": "Custom Field",
  "dt": "Customer",
  "fetch_from": null,
  "fetch_if_empty": 0,
  "fieldname": "custom_comapny",
  "fieldtype": "Link",
  "hidden": 0,
  "hide_border": 0,
  "hide_days": 0,
  "hide_seconds": 0,
  "ignore_user_permissions": 0,
  "ignore_xss_filter": 0,
  "in_global_search": 0,
  "in_list_view": 0,
  "in_preview": 0,
  "in_standard_filter": 0,
  "insert_after": "customer_name",
  "is_system_generated": 0,
  "is_virtual": 0,
  "label": "Company",
  "length": 0,
  "mandatory_depends_on": null,
  "modified": "2023-12-27 18:46:19.141175",
  "module": "Ambica Finance",
  "name": "Customer-custom_comapny",
  "no_copy": 0,
  "non_negative": 0,
  "options": "Company",
  "permlevel": 0,
  "precision": "",
  "print_hide": 0,
  "print_hide_if_no_value": 0,
  "print_width": null,
  "read_only": 0,
  "read_only_depends_on": null,
  "report_hide": 0,
  "reqd": 0,
  "search_index": 0,
  "sort_options": 0,
  "translatable": 0,
  "unique": 0,
  "width": null
 },
 {
  "allow_in_quick_entry": 0,
  "allow_on_submit": 0,
  "bold": 0,
  "collapsible": 0,
  "collapsible_depends_on": null,
  "columns": 0,
  "default": null,
  "depends_on": null,
  "description": null,
  "docstatus": 0,
  "doctype": "Custom Field",
  "dt": "Journal Entry",
  "fetch_from": null,
  "fetch_if_empty": 0,
  "fieldname": "custom_to_date",
  "fieldtype": "Date",
  "hidden": 0,
  "hide_border": 0,
  "hide_days": 0,
  "hide_seconds": 0,
  "ignore_user_permissions": 0,
  "ignore_xss_filter": 0,
  "in_global_search": 0,
  "in_list_view": 0,
  "in_preview": 0,
  "in_standard_filter": 0,
  "insert_after": "custom_from_date",
  "is_system_generated": 0,
  "is_virtual": 0,
  "label": "To Date",
  "length": 0,
  "mandatory_depends_on": null,
  "modified": "2023-12-27 18:46:19.720834",
  "module": "Ambica Finance",
  "name": "Journal Entry-custom_to_date",
  "no_copy": 0,
  "non_negative": 0,
  "options": null,
  "permlevel": 0,
  "precision": "",
  "print_hide": 0,
  "print_hide_if_no_value": 0,
  "print_width": null,
  "read_only": 1,
  "read_only_depends_on": null,
  "report_hide": 0,
  "reqd": 0,
  "search_index": 0,
  "sort_options": 0,
  "translatable": 0,
  "unique": 0,
  "width": null
 },
 {
  "allow_in_quick_entry": 0,
  "allow_on_submit": 0,
  "bold": 0,
  "collapsible": 0,
  "collapsible_depends_on": null,
  "columns": 1,
  "default": null,
  "depends_on": "eval:doc.due_date_based_on == 'Day(s) after invoice date';",
  "description": null,
  "docstatus": 0,
  "doctype": "Custom Field",
  "dt": "Payment Terms Template Detail",
  "fetch_from": null,
  "fetch_if_empty": 0,
  "fieldname": "custom_supplier_invoice",
  "fieldtype": "Check",
  "hidden": 0,
  "hide_border": 0,
  "hide_days": 0,
  "hide_seconds": 0,
  "ignore_user_permissions": 0,
  "ignore_xss_filter": 0,
  "in_global_search": 0,
  "in_list_view": 1,
  "in_preview": 0,
  "in_standard_filter": 0,
  "insert_after": "due_date_based_on",
  "is_system_generated": 0,
  "is_virtual": 0,
  "label": "Supplier Invoice",
  "length": 0,
  "mandatory_depends_on": null,
  "modified": "2023-12-27 18:46:20.269766",
  "module": "Ambica Finance",
  "name": "Payment Terms Template Detail-custom_supplier_invoice",
  "no_copy": 0,
  "non_negative": 0,
  "options": null,
  "permlevel": 0,
  "precision": "",
  "print_hide": 0,
  "print_hide_if_no_value": 0,
  "print_width": null,
  "read_only": 0,
  "read_only_depends_on": null,
  "report_hide": 0,
  "reqd": 0,
  "search_index": 0,
  "sort_options": 0,
  "translatable": 0,
  "unique": 0,
  "width": null
 },
 {
  "allow_in_quick_entry": 0,
  "allow_on_submit": 0,
  "bold": 0,
  "collapsible": 0,
  "collapsible_depends_on": null,
  "columns": 0,
  "default": null,
  "depends_on": null,
  "description": null,
  "docstatus": 0,
  "doctype": "Custom Field",
  "dt": "Supplier",
  "fetch_from": null,
  "fetch_if_empty": 0,
  "fieldname": "custom_import",
  "fieldtype": "Check",
  "hidden": 0,
  "hide_border": 0,
  "hide_days": 0,
  "hide_seconds": 0,
  "ignore_user_permissions": 0,
  "ignore_xss_filter": 0,
  "in_global_search": 0,
  "in_list_view": 0,
  "in_preview": 0,
  "in_standard_filter": 0,
  "insert_after": "is_transporter",
  "is_system_generated": 0,
  "is_virtual": 0,
  "label": "Import",
  "length": 0,
  "mandatory_depends_on": null,
  "modified": "2023-12-27 18:46:19.624463",
  "module": "Ambica Finance",
  "name": "Supplier-custom_import",
  "no_copy": 0,
  "non_negative": 0,
  "options": null,
  "permlevel": 0,
  "precision": "",
  "print_hide": 0,
  "print_hide_if_no_value": 0,
  "print_width": null,
  "read_only": 0,
  "read_only_depends_on": null,
  "report_hide": 0,
  "reqd": 0,
  "search_index": 0,
  "sort_options": 0,
  "translatable": 0,
  "unique": 0,
  "width": null
 },
 {
  "allow_in_quick_entry": 0,
  "allow_on_submit": 0,
  "bold": 0,
  "collapsible": 0,
  "collapsible_depends_on": null,
  "columns": 0,
  "default": null,
  "depends_on": null,
  "description": null,
  "docstatus": 0,
  "doctype": "Custom Field",
  "dt": "Purchase Invoice",
  "fetch_from": null,
  "fetch_if_empty": 0,
  "fieldname": "custom_supplier_invoice_date",
  "fieldtype": "Date",
  "hidden": 1,
  "hide_border": 0,
  "hide_days": 0,
  "hide_seconds": 0,
  "ignore_user_permissions": 0,
  "ignore_xss_filter": 0,
  "in_global_search": 0,
  "in_list_view": 0,
  "in_preview": 0,
  "in_standard_filter": 0,
  "insert_after": "bill_date",
  "is_system_generated": 0,
  "is_virtual": 0,
  "label": "custom Supplier Invoice Date",
  "length": 0,
  "mandatory_depends_on": null,
  "modified": "2023-12-27 18:46:19.990807",
  "module": "Ambica Finance",
  "name": "Purchase Invoice-custom_supplier_invoice_date",
  "no_copy": 0,
  "non_negative": 0,
  "options": null,
  "permlevel": 0,
  "precision": "",
  "print_hide": 0,
  "print_hide_if_no_value": 0,
  "print_width": null,
  "read_only": 0,
  "read_only_depends_on": null,
  "report_hide": 0,
  "reqd": 0,
  "search_index": 0,
  "sort_options": 0,
  "translatable": 0,
  "unique": 0,
  "width": null
 },
 {
  "allow_in_quick_entry": 0,
  "allow_on_submit": 0,
  "bold": 0,
  "collapsible": 0,
  "collapsible_depends_on": null,
  "columns": 0,
  "default": null,
  "depends_on": null,
  "description": null,
  "docstatus": 0,
  "doctype": "Custom Field",
  "dt": "Customer",
  "fetch_from": null,
  "fetch_if_empty": 0,
  "fieldname": "custom_turn_over_more_then_10cr",
  "fieldtype": "Select",
  "hidden": 0,
  "hide_border": 0,
  "hide_days": 0,
  "hide_seconds": 0,
  "ignore_user_permissions": 0,
  "ignore_xss_filter": 0,
  "in_global_search": 0,
  "in_list_view": 0,
  "in_preview": 0,
  "in_standard_filter": 0,
  "insert_after": "tax_id",
  "is_system_generated": 0,
  "is_virtual": 0,
  "label": "Turn Over More then 10Cr",
  "length": 0,
  "mandatory_depends_on": null,
  "modified": "2023-12-27 18:46:19.508399",
  "module": "Ambica Finance",
  "name": "Customer-custom_turn_over_mote_then_10cr",
  "no_copy": 0,
  "non_negative": 0,
  "options": "Yes\nNo",
  "permlevel": 0,
  "precision": "",
  "print_hide": 0,
  "print_hide_if_no_value": 0,
  "print_width": null,
  "read_only": 0,
  "read_only_depends_on": null,
  "report_hide": 0,
  "reqd": 0,
  "search_index": 0,
  "sort_options": 0,
  "translatable": 1,
  "unique": 0,
  "width": null
 },
 {
  "allow_in_quick_entry": 0,
  "allow_on_submit": 0,
  "bold": 0,
  "collapsible": 0,
  "collapsible_depends_on": null,
  "columns": 0,
  "default": null,
  "depends_on": "",
  "description": null,
  "docstatus": 0,
  "doctype": "Custom Field",
  "dt": "Customer",
  "fetch_from": null,
  "fetch_if_empty": 0,
  "fieldname": "custom_tds_declaration",
  "fieldtype": "Attach",
  "hidden": 0,
  "hide_border": 0,
  "hide_days": 0,
  "hide_seconds": 0,
  "ignore_user_permissions": 0,
  "ignore_xss_filter": 0,
  "in_global_search": 0,
  "in_list_view": 0,
  "in_preview": 0,
  "in_standard_filter": 0,
  "insert_after": "custom_turn_over_more_then_10cr",
  "is_system_generated": 0,
  "is_virtual": 0,
  "label": "TDS Declaration",
  "length": 0,
  "mandatory_depends_on": null,
  "modified": "2023-12-27 18:46:19.410118",
  "module": "Ambica Finance",
  "name": "Customer-custom_tds_declaration",
  "no_copy": 0,
  "non_negative": 0,
  "options": null,
  "permlevel": 0,
  "precision": "",
  "print_hide": 0,
  "print_hide_if_no_value": 0,
  "print_width": null,
  "read_only": 0,
  "read_only_depends_on": null,
  "report_hide": 0,
  "reqd": 0,
  "search_index": 0,
  "sort_options": 0,
  "translatable": 0,
  "unique": 0,
  "width": null
 }
]