{
 "add_total_row": 1,
 "columns": [],
 "creation": "2024-02-06 16:18:05.509582",
 "disabled": 0,
 "docstatus": 0,
 "doctype": "Report",
 "filters": [],
 "idx": 0,
 "is_standard": "Yes",
 "letterhead": null,
 "modified": "2024-02-07 18:25:30.570332",
 "modified_by": "Administrator",
 "module": "Ambica Finance",
 "name": "Purchase register for Tax Audit Report",
 "owner": "Administrator",
 "prepared_report": 0,
 "query": "SELECT\n    PI.bill_type AS 'Purchase Type',\n    PI.name AS 'Document Code',\n    PI.posting_date AS 'Document Date',\n    PI.bill_no AS 'Bill No.',\n    PI.bill_date AS 'Bill Date',\n    PII.expense_account AS 'Name of Expense',\n    PII.item_name AS 'Item Name',\n    PII.gst_hsn_code AS 'HSN Code',\n    PI.supplier AS 'Party Name',\n    S.gst_category AS 'GST Category',\n    S.gstin AS 'GST No.',\n    POI.qty AS 'PO Qty.',\n    PII.uom AS 'UOM',\n    PII.qty AS 'Invoice Qty.',\n    PII.rate AS 'Basic Rate',\n    PII.discount_percentage AS 'Disc. Per.',\n    PII.discount_amount AS 'Item Wise Disc.',\n    PII.amount AS 'Gross Amount',\n    PI.additional_discount_percentage AS 'All Disc. Per.',\n    PI.discount_amount AS 'Discount Amt.',\n    (PII.amount-PII.discount_amount) AS 'Basic Amt.',\n    PI.currency AS 'Freight (P)',\n    PI.currency AS 'Other Chg.',\n    PI.currency AS 'Pack && For Chrgs.',\n    PI.rounding_adjustment AS 'R.Off (P-M)',\n    PI.rounding_adjustment AS 'R.Off (P-P)',\n    PI.grand_total AS 'Net Taxable Amt.',\n    (PII.cgst_rate+PII.sgst_rate+PII.igst_rate) AS 'Per. of Tax',\n    PII.cgst_amount AS 'CGST (P)',\n    PII.sgst_amount AS 'SGST (P)',\n    PII.igst_amount AS 'IGST (P)',\n    PI.currency AS 'Other Charges w/o GST',\n    PI.rounded_total AS 'Total Amount',\n    CASE\n        WHEN PI.tax_category='Out-State' THEN 'Inter-State'\n        WHEN PI.tax_category='In-State' THEN 'Local'\n    END AS 'GST Type',\n    PII.purchase_order AS 'PO No.',\n    PI.owner AS 'Entered By',\n    PI.owner AS 'Passed By',\n    PI.modified_by AS 'Approved By'\nFROM\n    `tabPurchase Invoice` AS PI\nLEFT JOIN\n    `tabPurchase Invoice Item` AS PII ON PI.name = PII.parent\nLEFT JOIN\n    `tabSupplier` AS S ON S.name = PI.supplier\nLEFT JOIN\n    `tabPurchase Order` AS PO ON PO.name = PII.purchase_order\nLEFT JOIN\n    `tabPurchase Order Item` AS POI ON PO.name = POI.parent AND PII.item_code = POI.item_code\nORDER BY\n    PI.creation DESC;",
 "ref_doctype": "Purchase Invoice",
 "reference_report": "",
 "report_name": "Purchase register for Tax Audit Report",
 "report_type": "Query Report",
 "roles": []
}